fastapi_cli_tool/__init__.py
fastapi_cli_tool/__main__.py
fastapi_cli_tool/config.py
fastapi_cli_tool/constants.py
fastapi_cli_tool/context.py
fastapi_cli_tool/generator.py
fastapi_cli_tool/helpers.py
fastapi_cli_tool/main.py
fastapi_cli_tool/templates/__init__.py
fastapi_cli_tool/templates/app/__init__.py
fastapi_cli_tool/templates/app/cookiecutter.json
fastapi_cli_tool/templates/app/hooks/post_gen_project.py
fastapi_cli_tool/templates/app/{{ cookiecutter.folder_name }}/__init__.py
fastapi_cli_tool/templates/app/{{ cookiecutter.folder_name }}/api/__init__.py
fastapi_cli_tool/templates/app/{{ cookiecutter.folder_name }}/api/routes_delete.py
fastapi_cli_tool/templates/app/{{ cookiecutter.folder_name }}/api/routes_get.py
fastapi_cli_tool/templates/app/{{ cookiecutter.folder_name }}/api/routes_patch.py
fastapi_cli_tool/templates/app/{{ cookiecutter.folder_name }}/api/routes_post.py
fastapi_cli_tool/templates/app/{{ cookiecutter.folder_name }}/api/routes_put.py
fastapi_cli_tool/templates/app/{{ cookiecutter.folder_name }}/crud/__init__.py
fastapi_cli_tool/templates/app/{{ cookiecutter.folder_name }}/crud/crud_delete.py
fastapi_cli_tool/templates/app/{{ cookiecutter.folder_name }}/crud/crud_get.py
fastapi_cli_tool/templates/app/{{ cookiecutter.folder_name }}/crud/crud_post.py
fastapi_cli_tool/templates/app/{{ cookiecutter.folder_name }}/crud/crud_update.py
fastapi_cli_tool/templates/app/{{ cookiecutter.folder_name }}/models.py
fastapi_cli_tool/templates/app/{{ cookiecutter.folder_name }}/schema.py
fastapi_cli_tool/templates/app/{{ cookiecutter.folder_name }}/urls.py
fastapi_cli_tool/templates/project/__init__.py
fastapi_cli_tool/templates/project/cookiecutter.json
fastapi_cli_tool/templates/project/hooks/post_gen_project.py
fastapi_cli_tool/templates/project/{{ cookiecutter.folder_name }}/backend/__init__.py
fastapi_cli_tool/templates/project/{{ cookiecutter.folder_name }}/backend/middleware.py
fastapi_cli_tool-0.1.3.dist-info/entry_points.txt
fastapi_cli_tool-0.1.3.dist-info/METADATA
fastapi_cli_tool-0.1.3.dist-info/WHEEL
fastapi_cli_tool-0.1.3.dist-info/RECORD
